infer/__init__.py
infer/yolov5_openvino.py
labels_tool/__init__.py
labels_tool/auto_label.py
labels_tool/py_tools.py
cvtools_python-0.0.1.dist-info/LICENSE.txt
cvtools_python-0.0.1.dist-info/METADATA
cvtools_python-0.0.1.dist-info/WHEEL
cvtools_python-0.0.1.dist-info/top_level.txt
cvtools_python-0.0.1.dist-info/RECORD
