Metadata-Version: 2.1
Name: cvtools-python
Version: 0.0.1
Summary: A small tool package
Home-page: https://github.com/1402091247/pytools
Author: Nxp
Author-email: 1402091247@qq.com
Classifier: Programming Language :: Python :: 3
Classifier: License :: OSI Approved :: MIT License
Classifier: Operating System :: OS Independent
Requires-Python: >=3.6
License-File: LICENSE.txt
